azelia/__init__.py
azelia/azelia.py
azelia/azeliaconfig.py
azelia/config.py
azelia/password_handler.py
azelia/password_policies.py
Azelia_hash-0.1.1.dist-info/LICENCE
Azelia_hash-0.1.1.dist-info/METADATA
Azelia_hash-0.1.1.dist-info/WHEEL
Azelia_hash-0.1.1.dist-info/top_level.txt
Azelia_hash-0.1.1.dist-info/RECORD
