Metadata-Version: 2.1
Name: Azelia-hash
Version: 0.1.1
Summary: A combination of 2 hashing algorithms
Home-page: https://github.com/Penuts8773/Azelia-hash
Author: john chris
Author-email: idiomajohnchris049@gmail.com
Classifier: Programming Language :: Python :: 3
Classifier: License :: OSI Approved :: MIT License
Classifier: Operating System :: OS Independent
License-File: LICENCE
Requires-Dist: argon2-cffi==21.1.0
Requires-Dist: bcrypt==3.2.0
Requires-Dist: mysql-connector-python==8.0.27
Requires-Dist: pymysql==1.0.2
